Librarygold/__init__.py
Librarygold/goldratio.py
nim33423320-0.0.1.dist-info/LICENSE
nim33423320-0.0.1.dist-info/METADATA
nim33423320-0.0.1.dist-info/WHEEL
nim33423320-0.0.1.dist-info/top_level.txt
nim33423320-0.0.1.dist-info/RECORD
