Metadata-Version: 2.1
Name: nim33423320
Version: 0.0.1
Summary: Golden Ratio
Home-page: https://github.com/rizalfarhan
Author: rizalfarhann
Author-email: rizalfarhannanda@gmail.com
License: MIT
Keywords: Hello
Platform: UNKNOWN
Classifier: Development Status :: 1 - Planning
